helloCode/__init__.py
helloCode/hello.py
hellow_worldo-0.0.17.dist-info/METADATA
hellow_worldo-0.0.17.dist-info/WHEEL
hellow_worldo-0.0.17.dist-info/top_level.txt
hellow_worldo-0.0.17.dist-info/RECORD
