Metadata-Version: 2.1
Name: hellow-worldo
Version: 0.0.17
Summary: hello world
Home-page: UNKNOWN
Author: RohitMishra (The Great DEV)
Author-email: RKMDEV@DEV.com
License: UNKNOWN
Keywords: python,hello
Platform: UNKNOWN
Classifier: Development Status :: 5 - Production/Stable
Classifier: Intended Audience :: Developers
Classifier: Programming Language :: Python :: 3
Classifier: Operating System :: Unix
Classifier: Operating System :: MacOS :: MacOS X
Classifier: Operating System :: Microsoft :: Windows
